spark-ui-tab/__init__.py
spark-ui-tab/serverextension.py
spark_ui_tab/__init__.py
spark_ui_tab/serverextension.py
spark_ui_tab/spark_not_found.html
jupyterlab_spark_ui_tab-0.0.14.dist-info/LICENSE
jupyterlab_spark_ui_tab-0.0.14.dist-info/METADATA
jupyterlab_spark_ui_tab-0.0.14.dist-info/WHEEL
jupyterlab_spark_ui_tab-0.0.14.dist-info/top_level.txt
jupyterlab_spark_ui_tab-0.0.14.dist-info/RECORD
