Metadata-Version: 2.1
Name: jupyterlab-spark-ui-tab
Version: 0.0.14
Summary: Spark UI extension for jupyterlab
Home-page: https://github.com/Liorba/jupyterlab-spark-ui-tab
Author: Lior Baber
Author-email: liorbaber@gmail.com
License: apache-2.0
Keywords: jupyter,extension,spark
Platform: UNKNOWN
Classifier: Intended Audience :: Developers
Classifier: License :: OSI Approved :: Apache Software License
Classifier: Programming Language :: Python :: 3
Requires-Dist: bs4
